.gitignore
LICENSE
MANIFEST.in
NOTICE
README.rst
THANKS
TODO.md
pyproject.toml
setup.py
examples/httpparser.py
examples/httpparser_from_file.py
examples/httpstream.py
examples/test_issue23.py
toil_http_parser/__init__.py
toil_http_parser/_socketio.py
toil_http_parser/http.py
toil_http_parser/parser.c
toil_http_parser/parser.cpython-36m-x86_64-linux-gnu.so
toil_http_parser/parser.cpython-37m-x86_64-linux-gnu.so
toil_http_parser/parser.pyx
toil_http_parser/pyparser.py
toil_http_parser/pyversion_compat.h
toil_http_parser/reader.py
toil_http_parser/toil_http_parser.c
toil_http_parser/toil_http_parser.gyp
toil_http_parser/toil_http_parser.h
toil_http_parser/util.py
toil_http_parser.egg-info/PKG-INFO
toil_http_parser.egg-info/SOURCES.txt
toil_http_parser.egg-info/dependency_links.txt
toil_http_parser.egg-info/top_level.txt
toil_http_parser/__pycache__/__init__.cpython-36.pyc
toil_http_parser/__pycache__/__init__.cpython-37.pyc