Metadata-Version: 1.1
Name: toil-http-parser
Version: 0.8.9
Summary: http request/response parser
Home-page: https://github.com/DailyDreaming/toil-http-parser
Author: Benoit Chesneau is the real author; DailyDreaming is temporarily forking this as a py3.7 fix
Author-email: benoitc@e-engura.com
License: MIT
Platform: any
Classifier: Development Status :: 4 - Beta
Classifier: Environment :: Other Environment
Classifier: Intended Audience :: Developers
Classifier: License :: OSI Approved :: MIT License
Classifier: Operating System :: MacOS :: MacOS X
Classifier: Operating System :: POSIX
Classifier: Programming Language :: Python
Classifier: Programming Language :: Python :: 2.6
Classifier: Programming Language :: Python :: 2.7
Classifier: Programming Language :: Python :: 3
Classifier: Topic :: Internet
Classifier: Topic :: Utilities
Classifier: Topic :: Software Development :: Libraries :: Python Modules
